arts.py
lexer.py
main.py
node_data.py
parser.py
pipeline.py
renderer.py
symbols_art.py
texicode-1.0.1.dist-info/licenses/LICENSE
texicode-1.0.1.dist-info/METADATA
texicode-1.0.1.dist-info/WHEEL
texicode-1.0.1.dist-info/entry_points.txt
texicode-1.0.1.dist-info/top_level.txt
texicode-1.0.1.dist-info/RECORD
